rmw_fastrtps_cpp/_dummy.cpython-313-x86_64-linux-gnu.so
ros_rmw_fastrtps_cpp-9.3.3.data/data/include/rmw_fastrtps_cpp/rmw_fastrtps_cpp/MessageTypeSupport.hpp
ros_rmw_fastrtps_cpp-9.3.3.data/data/include/rmw_fastrtps_cpp/rmw_fastrtps_cpp/ServiceTypeSupport.hpp
ros_rmw_fastrtps_cpp-9.3.3.data/data/include/rmw_fastrtps_cpp/rmw_fastrtps_cpp/TypeSupport.hpp
ros_rmw_fastrtps_cpp-9.3.3.data/data/include/rmw_fastrtps_cpp/rmw_fastrtps_cpp/get_client.hpp
ros_rmw_fastrtps_cpp-9.3.3.data/data/include/rmw_fastrtps_cpp/rmw_fastrtps_cpp/get_participant.hpp
ros_rmw_fastrtps_cpp-9.3.3.data/data/include/rmw_fastrtps_cpp/rmw_fastrtps_cpp/get_publisher.hpp
ros_rmw_fastrtps_cpp-9.3.3.data/data/include/rmw_fastrtps_cpp/rmw_fastrtps_cpp/get_service.hpp
ros_rmw_fastrtps_cpp-9.3.3.data/data/include/rmw_fastrtps_cpp/rmw_fastrtps_cpp/get_subscriber.hpp
ros_rmw_fastrtps_cpp-9.3.3.data/data/include/rmw_fastrtps_cpp/rmw_fastrtps_cpp/identifier.hpp
ros_rmw_fastrtps_cpp-9.3.3.data/data/include/rmw_fastrtps_cpp/rmw_fastrtps_cpp/init_rmw_context_impl.hpp
ros_rmw_fastrtps_cpp-9.3.3.data/data/include/rmw_fastrtps_cpp/rmw_fastrtps_cpp/publisher.hpp
ros_rmw_fastrtps_cpp-9.3.3.data/data/include/rmw_fastrtps_cpp/rmw_fastrtps_cpp/serialization_format.hpp
ros_rmw_fastrtps_cpp-9.3.3.data/data/include/rmw_fastrtps_cpp/rmw_fastrtps_cpp/subscription.hpp
ros_rmw_fastrtps_cpp-9.3.3.data/data/include/rmw_fastrtps_cpp/rmw_fastrtps_cpp/visibility_control.h
ros_rmw_fastrtps_cpp-9.3.3.data/data/lib/librmw_fastrtps_cpp.so
ros_rmw_fastrtps_cpp-9.3.3.data/data/share/ament_index/resource_index/package_run_dependencies/rmw_fastrtps_cpp
ros_rmw_fastrtps_cpp-9.3.3.data/data/share/ament_index/resource_index/packages/rmw_fastrtps_cpp
ros_rmw_fastrtps_cpp-9.3.3.data/data/share/ament_index/resource_index/parent_prefix_path/rmw_fastrtps_cpp
ros_rmw_fastrtps_cpp-9.3.3.data/data/share/ament_index/resource_index/rmw_typesupport/rmw_fastrtps_cpp
ros_rmw_fastrtps_cpp-9.3.3.dist-info/METADATA
ros_rmw_fastrtps_cpp-9.3.3.dist-info/WHEEL
ros_rmw_fastrtps_cpp-9.3.3.dist-info/top_level.txt
ros_rmw_fastrtps_cpp-9.3.3.dist-info/RECORD
